strompris/PriceSource.py
strompris/__init__.py
strompris/common.py
strompris/const.py
strompris/schemas.py
strompris/strompris.py
pyStrompris-0.0.11.dist-info/LICENSE.md
pyStrompris-0.0.11.dist-info/METADATA
pyStrompris-0.0.11.dist-info/WHEEL
pyStrompris-0.0.11.dist-info/top_level.txt
pyStrompris-0.0.11.dist-info/RECORD
