Metadata-Version: 2.1
Name: pyStrompris
Version: 0.0.11
Summary: A python3 library to read electricity price
Home-page: https://github.com/bskjon/pyStrompris
Author: Brage Skjønborg
Author-email: bskjon@outlook.com
Classifier: Intended Audience :: Developers
Classifier: Operating System :: OS Independent
Classifier: Programming Language :: Python
Classifier: Programming Language :: Python :: 3
Classifier: Topic :: Home Automation
Classifier: Topic :: Software Development :: Libraries :: Python Modules
Requires-Python: >=3.9.0
License-File: LICENSE.md
Requires-Dist: aiohttp (>=3.8.1)
Requires-Dist: pytz (>=2019.3)
